{
  "doorStatesAlt": {
    "0": [
      "Door 2",
      "Door 6",
      "Door 8",
      "Door 13",
      "Door 17",
      "Door 19",
      "Door 25",
      "Door 28",
      "Door 31",
      "Door 33",
      "Door 34",
      "Door 35",
      "Door 38",
      "Door 40",
      "Door 42",
      "Door 45",
      "Door 54",
      "Door 55",
      "Door 60",
      "Door 63",
      "Door 64",
      "Door 66",
      "Door 73",
      "Door 74",
      "Door 75",
      "Door 77",
      "Door 80",
      "Door 82",
      "Door 83",
      "Door 84",
      "Door 86",
      "Door 87",
      "Door 92",
      "Door 95",
      "Door 96",
      "Door 103",
      "Door 105",
      "Door 107",
      "Door 109",
      "Door 112",
      "Door 116",
      "Door 117",
      "Door 122",
      "Door 124",
      "Door 127",
      "Door 129",
      "Door 130",
      "Door 134",
      "Door 135",
      "Door 137",
      "Door 140",
      "Door 141",
      "Door 142",
      "Door 144",
      "Door 149",
      "Door 151",
      "Door 153",
      "Door 158",
      "Door 160",
      "Door 163",
      "Door 167",
      "Door 172",
      "Door 174",
      "Door 176",
      "Door 177",
      "Door 179",
      "Door 181",
      "Door 186",
      "Door 189",
      "Door 191",
      "Door 193",
      "Door 195",
      "Door 197",
      "Door 198",
      "Door 200",
      "Door 201",
      "Door 203",
      "Door 209",
      "Door 214",
      "Door 218",
      "Door 220",
      "Door 221",
      "Door 223",
      "Door 224",
      "Door 226",
      "Door 227",
      "Door 228",
      "Door 233",
      "Door 238",
      "Door 240",
      "Door 241",
      "Door 250",
      "Door 253",
      "Door 261",
      "Door 264",
      "Door 266",
      "Door 267",
      "Door 270",
      "Door 271",
      "Door 274",
      "Door 276",
      "Door 278",
      "Door 280",
      "Door 282",
      "Door 288",
      "Door 289",
      "Door 293",
      "Door 295",
      "Door 299",
      "Door 301",
      "Door 306",
      "Door 313",
      "Door 314",
      "Door 318",
      "Door 319",
      "Door 320",
      "Door 321",
      "Door 323",
      "Door 327",
      "Door 331",
      "Door 333",
      "Door 339",
      "Door 341",
      "Door 344",
      "Door 346",
      "Door 350",
      "Door 351",
      "Door 352",
      "Door 359",
      "Door 361",
      "Door 364",
      "Door 365",
      "Door 369",
      "Door 372",
      "Door 373",
      "Door 374",
      "Door 376",
      "Door 378",
      "Door 382",
      "Door 384",
      "Door 386",
      "Door 389",
      "Door 391",
      "Door 393",
      "Door 396",
      "Door 398",
      "Door 402",
      "Door 406",
      "Door 409",
      "Door 412",
      "Door 420",
      "Door 421",
      "Door 422",
      "Door 426",
      "Door 428",
      "Door 429",
      "Door 430",
      "Door 431",
      "Door 432",
      "Door 434",
      "Door 438",
      "Door 439",
      "Door 444",
      "Door 454",
      "Door 455",
      "Door 456",
      "Door 457",
      "Door 458",
      "Door 459",
      "Door 461",
      "Door 462",
      "Door 466",
      "Door 468",
      "Door 476"
    ],
    "1": [
      "Door 75",
      "Door 116",
      "Door 172"
    ],
    "2": [
      "Door 141",
      "Door 165",
      "Door 277",
      "Door 306"
    ],
    "3": [
      "Door 33",
      "Door 64",
      "Door 237",
      "Door 238",
      "Door 259"
    ],
    "4": [
      "Door 38",
      "Door 64",
      "Door 78",
      "Door 96",
      "Door 257",
      "Door 287",
      "Door 368"
    ],
    "5": [
      "Door 31",
      "Door 52",
      "Door 98",
      "Door 144",
      "Door 327"
    ],
    "6": [
      "Door 82",
      "Door 132",
      "Door 172",
      "Door 215",
      "Door 347",
      "Door 459"
    ],
    "7": [
      "Door 98",
      "Door 168",
      "Door 179",
      "Door 224",
      "Door 288",
      "Door 364"
    ],
    "8": [
      "Door 47",
      "Door 106",
      "Door 190",
      "Door 310",
      "Door 448"
    ],
    "9": [
      "Door 33",
      "Door 35",
      "Door 69",
      "Door 75",
      "Door 130"
    ],
    "10": [
      "Door 86",
      "Door 278"
    ],
    "11": [
      "Door 27",
      "Door 86"
    ],
    "12": [
      "Door 130",
      "Door 186",
      "Door 266",
      "Door 329",
      "Door 403",
      "Door 410"
    ],
    "13": [
      "Door 20",
      "Door 71",
      "Door 254",
      "Door 350",
      "Door 364"
    ],
    "14": [
      "Door 78",
      "Door 258",
      "Door 406",
      "Door 431"
    ],
    "15": [
      "Door 34",
      "Door 35",
      "Door 38",
      "Door 57",
      "Door 105",
      "Door 190"
    ],
    "16": [
      "Door 116",
      "Door 144",
      "Door 151",
      "Door 190",
      "Door 261",
      "Door 266",
      "Door 288"
    ],
    "17": [
      "Door 82",
      "Door 98",
      "Door 191",
      "Door 231",
      "Door 282",
      "Door 431"
    ],
    "18": [
      "Door 259",
      "Door 363"
    ],
    "19": [
      "Door 176",
      "Door 179",
      "Door 190",
      "Door 288",
      "Door 402",
      "Door 436"
    ],
    "20": [
      "Door 78",
      "Door 141",
      "Door 288"
    ],
    "21": [
      "Door 221",
      "Door 229",
      "Door 282",
      "Door 317"
    ],
    "22": [
      "Door 78",
      "Door 355"
    ],
    "23": [
      "Door 176"
    ],
    "24": [
      "Door 78",
      "Door 186",
      "Door 296",
      "Door 350",
      "Door 351",
      "Door 365"
    ],
    "25": [
      "Door 221",
      "Door 419",
      "Door 448"
    ],
    "26": [
      "Door 171",
      "Door 190",
      "Door 352",
      "Door 391",
      "Door 429"
    ],
    "27": [
      "Door 8",
      "Door 59",
      "Door 223",
      "Door 238",
      "Door 254"
    ],
    "28": [
      "Door 186",
      "Door 300"
    ],
    "29": [
      "Door 20",
      "Door 306",
      "Door 327",
      "Door 395",
      "Door 402"
    ],
    "30": [
      "Door 270",
      "Door 406"
    ],
    "31": [
      "Door 37",
      "Door 382"
    ],
    "32": [
      "Door 134"
    ],
    "33": [
      "Door 250"
    ],
    "34": [
      "Door 153",
      "Door 359"
    ],
    "35": [
      "Door 78",
      "Door 274",
      "Door 376"
    ],
    "36": [
      "Door 59",
      "Door 176"
    ],
    "37": [
      "Door 151",
      "Door 259",
      "Door 342",
      "Door 382"
    ],
    "38": [
      "Door 28",
      "Door 215",
      "Door 250",
      "Door 338",
      "Door 376"
    ],
    "39": [
      "Door 8",
      "Door 96",
      "Door 142",
      "Door 146",
      "Door 277",
      "Door 396"
    ],
    "40": [
      "Door 28",
      "Door 363",
      "Door 364",
      "Door 368"
    ],
    "41": [
      "Door 176",
      "Door 191",
      "Door 382",
      "Door 412",
      "Door 459"
    ],
    "42": [
      "Door 203",
      "Door 455"
    ],
    "43": [
      "Door 214",
      "Door 224",
      "Door 253",
      "Door 382"
    ],
    "44": [
      "Door 77",
      "Door 78",
      "Door 215",
      "Door 338",
      "Door 391",
      "Door 409"
    ],
    "45": [
      "Door 34",
      "Door 163",
      "Door 238",
      "Door 373",
      "Door 406"
    ],
    "46": [
      "Door 142"
    ],
    "47": [
      "Door 77",
      "Door 149",
      "Door 339",
      "Door 364"
    ],
    "48": [
      "Door 27",
      "Door 37",
      "Door 163",
      "Door 186",
      "Door 403",
      "Door 426"
    ],
    "49": [
      "Door 8",
      "Door 37",
      "Door 115",
      "Door 258",
      "Door 368"
    ]
  }
}