{
  "doorStatesAlt": {
    "0": [
      "Door 1",
      "Door 6",
      "Door 18",
      "Door 20",
      "Door 21",
      "Door 23",
      "Door 25",
      "Door 26",
      "Door 31",
      "Door 33",
      "Door 34",
      "Door 38",
      "Door 42",
      "Door 45",
      "Door 47",
      "Door 50",
      "Door 51",
      "Door 52",
      "Door 53",
      "Door 58",
      "Door 60",
      "Door 62",
      "Door 64",
      "Door 67",
      "Door 70",
      "Door 72",
      "Door 80",
      "Door 85",
      "Door 86",
      "Door 88",
      "Door 89",
      "Door 92",
      "Door 94",
      "Door 97",
      "Door 98",
      "Door 99",
      "Door 102",
      "Door 104",
      "Door 107",
      "Door 111",
      "Door 113",
      "Door 121",
      "Door 125",
      "Door 130",
      "Door 132",
      "Door 134",
      "Door 135",
      "Door 137",
      "Door 140",
      "Door 143",
      "Door 144",
      "Door 145",
      "Door 147",
      "Door 148",
      "Door 149",
      "Door 151",
      "Door 153",
      "Door 157",
      "Door 159",
      "Door 162",
      "Door 167",
      "Door 168",
      "Door 170",
      "Door 171",
      "Door 173",
      "Door 176",
      "Door 177",
      "Door 178",
      "Door 185",
      "Door 188",
      "Door 190",
      "Door 195",
      "Door 198",
      "Door 199",
      "Door 202",
      "Door 203",
      "Door 206",
      "Door 208",
      "Door 209",
      "Door 210",
      "Door 212",
      "Door 217",
      "Door 222",
      "Door 223",
      "Door 228",
      "Door 230",
      "Door 231",
      "Door 235",
      "Door 238",
      "Door 240",
      "Door 243",
      "Door 248",
      "Door 249",
      "Door 251",
      "Door 253",
      "Door 255",
      "Door 257",
      "Door 259",
      "Door 260",
      "Door 265",
      "Door 268",
      "Door 270",
      "Door 273",
      "Door 280",
      "Door 283",
      "Door 285",
      "Door 287",
      "Door 289",
      "Door 290",
      "Door 293",
      "Door 294",
      "Door 298",
      "Door 300",
      "Door 302",
      "Door 303",
      "Door 306",
      "Door 307",
      "Door 309",
      "Door 311",
      "Door 313",
      "Door 315",
      "Door 316",
      "Door 319",
      "Door 320",
      "Door 326",
      "Door 328",
      "Door 330",
      "Door 332",
      "Door 333",
      "Door 336",
      "Door 337",
      "Door 338",
      "Door 339",
      "Door 344",
      "Door 345",
      "Door 357",
      "Door 363",
      "Door 364",
      "Door 365",
      "Door 366",
      "Door 368",
      "Door 369",
      "Door 370",
      "Door 372",
      "Door 376",
      "Door 377",
      "Door 382",
      "Door 383",
      "Door 389",
      "Door 392",
      "Door 393",
      "Door 394",
      "Door 397",
      "Door 403",
      "Door 407",
      "Door 412",
      "Door 414",
      "Door 416",
      "Door 419",
      "Door 424",
      "Door 425",
      "Door 426",
      "Door 430",
      "Door 435",
      "Door 437",
      "Door 438",
      "Door 441",
      "Door 443",
      "Door 444",
      "Door 446",
      "Door 448",
      "Door 449",
      "Door 452",
      "Door 454",
      "Door 458",
      "Door 461",
      "Door 462",
      "Door 463",
      "Door 466",
      "Door 472",
      "Door 474"
    ],
    "1": [
      "Door 43",
      "Door 84",
      "Door 87",
      "Door 238",
      "Door 246",
      "Door 370",
      "Door 401"
    ],
    "2": [
      "Door 112",
      "Door 211",
      "Door 283",
      "Door 290"
    ],
    "3": [
      "Door 40",
      "Door 50",
      "Door 100",
      "Door 276",
      "Door 383",
      "Door 461"
    ],
    "4": [
      "Door 32",
      "Door 45",
      "Door 208",
      "Door 357",
      "Door 358",
      "Door 414"
    ],
    "5": [
      "Door 40",
      "Door 245",
      "Door 390"
    ],
    "6": [
      "Door 93",
      "Door 209",
      "Door 255",
      "Door 327",
      "Door 370"
    ],
    "7": [
      "Door 208",
      "Door 327",
      "Door 383",
      "Door 411"
    ],
    "8": [
      "Door 90",
      "Door 112",
      "Door 219"
    ],
    "9": [
      "Door 18",
      "Door 45",
      "Door 79",
      "Door 111",
      "Door 143",
      "Door 205",
      "Door 209",
      "Door 414",
      "Door 454"
    ],
    "10": [
      "Door 273",
      "Door 327",
      "Door 400",
      "Door 420"
    ],
    "11": [
      "Door 40",
      "Door 75",
      "Door 255",
      "Door 316"
    ],
    "12": [
      "Door 122",
      "Door 153",
      "Door 196"
    ],
    "13": [
      "Door 143",
      "Door 195",
      "Door 236",
      "Door 251",
      "Door 336",
      "Door 355",
      "Door 425"
    ],
    "14": [
      "Door 167",
      "Door 426",
      "Door 461"
    ],
    "15": [
      "Door 223",
      "Door 273",
      "Door 332",
      "Door 455"
    ],
    "16": [
      "Door 38",
      "Door 111",
      "Door 251",
      "Door 335",
      "Door 420"
    ],
    "17": [
      "Door 28",
      "Door 144",
      "Door 279",
      "Door 328",
      "Door 412"
    ],
    "18": [
      "Door 159",
      "Door 316",
      "Door 383"
    ],
    "19": [
      "Door 111",
      "Door 297"
    ],
    "20": [
      "Door 260",
      "Door 328"
    ],
    "21": [
      "Door 33",
      "Door 62",
      "Door 84",
      "Door 112",
      "Door 147",
      "Door 238",
      "Door 420",
      "Door 426"
    ],
    "22": [
      "Door 94",
      "Door 153",
      "Door 426"
    ],
    "23": [
      "Door 32",
      "Door 283",
      "Door 357"
    ],
    "24": [
      "Door 50",
      "Door 84",
      "Door 328",
      "Door 414"
    ],
    "25": [
      "Door 107",
      "Door 205"
    ],
    "26": [
      "Door 370"
    ],
    "27": [
      "Door 6",
      "Door 62",
      "Door 86",
      "Door 157",
      "Door 235",
      "Door 236"
    ],
    "28": [
      "Door 89",
      "Door 107",
      "Door 223",
      "Door 307",
      "Door 426"
    ],
    "29": [
      "Door 104",
      "Door 159",
      "Door 425",
      "Door 460"
    ],
    "30": [
      "Door 246",
      "Door 260",
      "Door 437",
      "Door 463"
    ],
    "31": [
      "Door 1",
      "Door 31",
      "Door 176",
      "Door 383"
    ],
    "32": [
      "Door 94",
      "Door 145",
      "Door 182",
      "Door 336",
      "Door 358",
      "Door 402"
    ],
    "33": [
      "Door 145",
      "Door 248",
      "Door 290",
      "Door 308"
    ],
    "34": [
      "Door 441"
    ],
    "35": [
      "Door 93",
      "Door 104",
      "Door 407",
      "Door 458"
    ],
    "36": [
      "Door 38",
      "Door 236",
      "Door 307",
      "Door 449"
    ],
    "37": [
      "Door 100",
      "Door 273",
      "Door 303",
      "Door 444",
      "Door 454"
    ],
    "38": [
      "Door 33",
      "Door 80",
      "Door 309"
    ],
    "39": [
      "Door 84",
      "Door 125",
      "Door 167",
      "Door 273",
      "Door 309",
      "Door 316"
    ],
    "40": [
      "Door 31",
      "Door 125",
      "Door 438"
    ],
    "41": [
      "Door 80",
      "Door 143",
      "Door 205",
      "Door 208",
      "Door 243",
      "Door 253"
    ],
    "42": [
      "Door 113",
      "Door 437"
    ],
    "43": [
      "Door 89",
      "Door 290",
      "Door 316",
      "Door 345",
      "Door 358",
      "Door 414"
    ],
    "44": [
      "Door 176",
      "Door 248",
      "Door 441"
    ],
    "45": [
      "Door 208",
      "Door 212",
      "Door 406",
      "Door 412"
    ],
    "46": [
      "Door 62",
      "Door 86",
      "Door 113",
      "Door 140",
      "Door 316"
    ],
    "47": [
      "Door 1",
      "Door 32",
      "Door 111",
      "Door 173",
      "Door 444"
    ],
    "48": [
      "Door 140",
      "Door 246",
      "Door 248"
    ],
    "49": [
      "Door 130",
      "Door 290",
      "Door 333",
      "Door 407",
      "Door 441",
      "Door 444"
    ]
  }
}