{
  "doorStatesAlt": {
    "0": [
      "Door 2",
      "Door 4",
      "Door 14",
      "Door 15",
      "Door 16",
      "Door 18",
      "Door 20",
      "Door 22",
      "Door 24",
      "Door 25",
      "Door 28",
      "Door 31",
      "Door 34",
      "Door 41",
      "Door 47",
      "Door 50",
      "Door 53",
      "Door 55",
      "Door 56",
      "Door 57",
      "Door 58",
      "Door 60",
      "Door 62",
      "Door 64",
      "Door 69",
      "Door 70",
      "Door 73",
      "Door 74",
      "Door 75",
      "Door 78",
      "Door 79",
      "Door 82",
      "Door 85",
      "Door 88",
      "Door 92",
      "Door 98",
      "Door 101",
      "Door 102"
    ],
    "1": [
      "Door 27",
      "Door 57",
      "Door 91",
      "Door 92",
      "Door 104"
    ],
    "2": [
      "Door 27",
      "Door 57",
      "Door 76",
      "Door 82",
      "Door 95"
    ],
    "3": [
      "Door 18",
      "Door 27",
      "Door 38",
      "Door 60",
      "Door 92",
      "Door 95",
      "Door 107"
    ],
    "4": [
      "Door 36",
      "Door 69",
      "Door 82",
      "Door 95"
    ],
    "5": [
      "Door 19",
      "Door 24",
      "Door 69",
      "Door 70",
      "Door 74",
      "Door 82",
      "Door 87"
    ],
    "6": [
      "Door 14",
      "Door 24",
      "Door 82",
      "Door 91"
    ],
    "7": [
      "Door 60"
    ],
    "8": [
      "Door 4",
      "Door 38",
      "Door 50",
      "Door 74"
    ],
    "9": [
      "Door 22",
      "Door 39",
      "Door 50",
      "Door 92"
    ],
    "10": [
      "Door 4",
      "Door 14"
    ],
    "11": [
      "Door 25",
      "Door 50",
      "Door 75",
      "Door 92"
    ],
    "12": [
      "Door 22",
      "Door 36",
      "Door 38",
      "Door 78",
      "Door 92"
    ],
    "13": [
      "Door 69",
      "Door 75",
      "Door 91",
      "Door 102"
    ],
    "14": [
      "Door 18",
      "Door 25"
    ],
    "15": [
      "Door 36",
      "Door 38",
      "Door 58",
      "Door 70",
      "Door 74",
      "Door 92",
      "Door 102"
    ],
    "16": [
      "Door 22",
      "Door 73",
      "Door 82",
      "Door 92"
    ],
    "17": [
      "Door 4",
      "Door 22",
      "Door 39",
      "Door 56",
      "Door 57",
      "Door 58",
      "Door 78",
      "Door 95"
    ],
    "18": [
      "Door 24",
      "Door 38",
      "Door 50",
      "Door 69"
    ],
    "19": [
      "Door 14",
      "Door 18",
      "Door 22",
      "Door 24"
    ],
    "20": [
      "Door 55",
      "Door 57",
      "Door 73",
      "Door 92",
      "Door 101",
      "Door 107"
    ],
    "21": [
      "Door 2",
      "Door 22"
    ],
    "22": [
      "Door 53",
      "Door 58",
      "Door 64",
      "Door 82",
      "Door 101"
    ],
    "23": [
      "Door 15",
      "Door 28",
      "Door 47",
      "Door 56",
      "Door 70",
      "Door 91"
    ],
    "24": [
      "Door 2",
      "Door 22",
      "Door 24",
      "Door 39",
      "Door 58",
      "Door 60",
      "Door 73",
      "Door 74",
      "Door 95"
    ],
    "25": [
      "Door 15",
      "Door 22",
      "Door 24",
      "Door 34",
      "Door 53",
      "Door 60",
      "Door 69",
      "Door 78"
    ],
    "26": [
      "Door 31",
      "Door 47"
    ],
    "27": [
      "Door 50",
      "Door 70",
      "Door 78",
      "Door 91",
      "Door 95"
    ],
    "28": [
      "Door 18",
      "Door 19",
      "Door 22",
      "Door 34",
      "Door 36",
      "Door 50",
      "Door 55",
      "Door 56"
    ],
    "29": [
      "Door 14",
      "Door 19",
      "Door 28",
      "Door 56",
      "Door 64",
      "Door 82",
      "Door 107"
    ],
    "30": [
      "Door 28",
      "Door 34",
      "Door 36"
    ],
    "31": [
      "Door 19",
      "Door 25",
      "Door 38",
      "Door 62",
      "Door 69",
      "Door 85"
    ],
    "32": [
      "Door 28",
      "Door 31"
    ],
    "33": [
      "Door 34",
      "Door 55",
      "Door 101"
    ],
    "34": [
      "Door 25",
      "Door 82",
      "Door 101"
    ],
    "35": [
      "Door 19",
      "Door 50",
      "Door 62",
      "Door 70",
      "Door 73"
    ],
    "36": [
      "Door 50",
      "Door 88"
    ],
    "37": [
      "Door 70",
      "Door 85"
    ],
    "38": [
      "Door 22",
      "Door 24",
      "Door 87"
    ],
    "39": [
      "Door 18",
      "Door 20",
      "Door 34",
      "Door 38",
      "Door 55",
      "Door 78",
      "Door 88",
      "Door 92",
      "Door 95"
    ],
    "40": [
      "Door 15",
      "Door 24"
    ],
    "41": [
      "Door 15",
      "Door 18"
    ],
    "42": [
      "Door 20",
      "Door 47",
      "Door 58",
      "Door 74"
    ],
    "43": [
      "Door 4",
      "Door 18",
      "Door 47"
    ],
    "44": [
      "Door 15",
      "Door 18",
      "Door 25",
      "Door 41",
      "Door 47",
      "Door 75",
      "Door 104"
    ],
    "45": [
      "Door 47",
      "Door 58",
      "Door 70",
      "Door 88",
      "Door 92"
    ],
    "46": [
      "Door 47",
      "Door 78",
      "Door 85",
      "Door 87",
      "Door 88",
      "Door 92"
    ],
    "47": [
      "Door 15",
      "Door 28",
      "Door 41",
      "Door 47",
      "Door 101"
    ],
    "48": [
      "Door 28",
      "Door 34",
      "Door 50",
      "Door 58",
      "Door 101"
    ],
    "49": [
      "Door 20",
      "Door 34",
      "Door 36",
      "Door 85"
    ]
  }
}